notifier_client/__init__.py
notifier_client/web_app_notifier_client.py
telegram_notifier_client-1.2.1.dist-info/METADATA
telegram_notifier_client-1.2.1.dist-info/WHEEL
telegram_notifier_client-1.2.1.dist-info/top_level.txt
telegram_notifier_client-1.2.1.dist-info/RECORD
