Metadata-Version: 2.1
Name: telegram-notifier-client
Version: 1.2.1
Summary: telegram_notifier_client
Home-page: https://github.com/deusfinance/notifier-client.git
Author: Metalica
Author-email: rorschach <rorschach45001@gmail.com>
Project-URL: Homepage, https://github.com/deusfinance/notifier-client
Project-URL: Issues, https://github.com/deusfinance/notifier-client/issues
Keywords: telegram notifier client
Classifier: Programming Language :: Python :: 3
Classifier: License :: OSI Approved :: MIT License
Classifier: Operating System :: OS Independent
Requires-Python: >=3.8
Requires-Dist: certifi
Requires-Dist: charset-normalizer
Requires-Dist: idna
Requires-Dist: requests
Requires-Dist: urllib3
